isos/__init__.py
isos/_error.py
isos/_option.py
isos/_result.py
isos/_util.py
isos/py.typed
isos-0.3.3.dist-info/METADATA
isos-0.3.3.dist-info/WHEEL
isos-0.3.3.dist-info/RECORD
