Metadata-Version: 2.4
Name: isos
Version: 0.3.3
Summary: Option and Result types for Python.
Author-email: gsmyridis <georgesmyr@icloud.com>
Requires-Python: >=3.12
